gdml_editor/__init__.py
gdml_editor/__main__.py
gdml_editor/gui.py
gdml_editor/run_vtkviewer.py
gdml_editor-1.0.3.dist-info/licenses/LICENSE
gdml_editor-1.0.3.dist-info/METADATA
gdml_editor-1.0.3.dist-info/WHEEL
gdml_editor-1.0.3.dist-info/entry_points.txt
gdml_editor-1.0.3.dist-info/top_level.txt
gdml_editor-1.0.3.dist-info/RECORD
