Metadata-Version: 2.4
Name: gdml-editor
Version: 1.0.3
Summary: A GUI application for editing GDML geometry files with user-defined materials support
Author: GDML Editor Contributors
License-Expression: MIT
Project-URL: Homepage, https://github.com/yourusername/gdml-editor
Project-URL: Documentation, https://github.com/yourusername/gdml-editor#readme
Project-URL: Repository, https://github.com/yourusername/gdml-editor
Project-URL: Bug Tracker, https://github.com/yourusername/gdml-editor/issues
Keywords: gdml,geant4,geometry,physics,detector,simulation
Classifier: Development Status :: 4 - Beta
Classifier: Intended Audience :: Science/Research
Classifier: Topic :: Scientific/Engineering :: Physics
Classifier: Programming Language :: Python :: 3
Classifier: Programming Language :: Python :: 3.10
Classifier: Programming Language :: Python :: 3.11
Classifier: Programming Language :: Python :: 3.12
Classifier: Operating System :: OS Independent
Requires-Python: >=3.10
License-File: LICENSE
Requires-Dist: pyg4ometry>=1.0.0
Requires-Dist: vtk>=9.0.0
Provides-Extra: dev
Requires-Dist: pytest>=7.0; extra == "dev"
Requires-Dist: pytest-cov; extra == "dev"
Requires-Dist: black; extra == "dev"
Requires-Dist: flake8; extra == "dev"
Requires-Dist: mypy; extra == "dev"
Dynamic: license-file
